<?xml version="1.0" encoding="UTF-8"?>
<?xml-stylesheet type="text/xsl" charset="UTF-8" href="/xslt/nascar/standings-v2.0.xsl"?>
<!-- Generation started @ 2021-06-20 02:13:34 UTC -->
<series xmlns="http://feed.elasticstats.com/schema/nascar/standings-v2.0.xsd" id="3e32047e-4ff3-4e35-a607-1546a2c32214" alias="CUP" name="NASCAR Cup Series">
  <season year="2019" id="d39477c5-3c73-4119-98f1-5b88958b524a">
    <driver rank="1" id="85c06960-3610-4eff-9ef2-18641b84c952" first_name="Kyle" last_name="Busch" full_name="Kyle Busch" status="ACT" points="5040" starts="36" wins="5" poles="1" stage_wins="11" chase_bonus="51" chase_wins="1" chase_stage_wins="1" top_5="17" top_10="27" top_15="30" top_20="32" dnf="2" laps_led="1582" laps_completed="10167" money="0.0" avg_start_position="12.2778" avg_finish_position="8.9444" avg_laps_completed="282.4167" laps_led_pct="15.56" in_chase="true"/>
    <driver rank="2" behind="-5" id="4d95ef3a-46cc-43c2-b340-c92cea2ed7f8" first_name="Martin" last_name="Truex" full_name="Martin Truex Jr" status="ACT" points="5035" starts="36" wins="7" poles="0" stage_wins="8" chase_bonus="49" chase_wins="3" chase_stage_wins="5" top_5="15" top_10="24" top_15="27" top_20="31" dnf="2" laps_led="1371" laps_completed="10152" money="0.0" avg_start_position="13.1111" avg_finish_position="9.75" avg_laps_completed="282.0" laps_led_pct="13.5" in_chase="true"/>
    <driver rank="3" behind="-7" id="9d18716c-fd73-48d4-b3da-44228c767b84" first_name="Kevin" last_name="Harvick" full_name="Kevin Harvick" status="ACT" points="5033" starts="36" wins="4" poles="5" stage_wins="6" chase_bonus="34" chase_wins="1" chase_stage_wins="1" top_5="15" top_10="26" top_15="29" top_20="30" dnf="3" laps_led="953" laps_completed="9804" money="0.0" avg_start_position="8.5" avg_finish_position="10.0278" avg_laps_completed="272.3333" laps_led_pct="9.72" in_chase="true"/>
    <driver rank="4" behind="-13" id="cb9d6f49-0044-4305-be9a-22d428e52c95" first_name="Denny" last_name="Hamlin" full_name="Denny Hamlin" status="ACT" points="5027" starts="36" wins="6" poles="3" stage_wins="6" chase_bonus="43" chase_wins="2" chase_stage_wins="3" top_5="19" top_10="24" top_15="28" top_20="31" dnf="1" laps_led="922" laps_completed="10124" money="0.0" avg_start_position="11.0" avg_finish_position="9.4722" avg_laps_completed="281.2222" laps_led_pct="9.11" in_chase="true"/>
    <driver rank="5" behind="-2660" id="894b273e-ce7d-446c-9ab0-d9a474ce9d7f" first_name="Joey" last_name="Logano" full_name="Joey Logano" status="ACT" points="2380" starts="36" wins="2" poles="2" stage_wins="11" chase_bonus="31" chase_wins="0" chase_stage_wins="3" top_5="12" top_10="21" top_15="26" top_20="31" dnf="0" laps_led="899" laps_completed="10221" money="0.0" avg_start_position="10.3333" avg_finish_position="10.75" avg_laps_completed="283.9167" laps_led_pct="8.8" in_chase="false"/>
    <driver rank="6" behind="-2701" id="a756eefd-801d-4214-ab1b-0b595c21c37d" first_name="Kyle" last_name="Larson" full_name="Kyle Larson" status="ACT" points="2339" starts="36" wins="1" poles="1" stage_wins="5" chase_bonus="11" chase_wins="1" chase_stage_wins="1" top_5="8" top_10="17" top_15="24" top_20="27" dnf="8" laps_led="529" laps_completed="9496" money="0.0" avg_start_position="12.9167" avg_finish_position="15.0556" avg_laps_completed="263.7778" laps_led_pct="5.57" in_chase="false"/>
    <driver rank="7" behind="-2701" id="67948099-4196-4e1b-ae9e-b437aa99000a" first_name="Ryan" last_name="Blaney" full_name="Ryan Blaney" status="ACT" points="2339" starts="36" wins="1" poles="1" stage_wins="2" chase_bonus="9" chase_wins="1" chase_stage_wins="0" top_5="11" top_10="18" top_15="25" top_20="26" dnf="4" laps_led="422" laps_completed="10001" money="0.0" avg_start_position="12.2778" avg_finish_position="13.7222" avg_laps_completed="277.8056" laps_led_pct="4.22" in_chase="false"/>
    <driver rank="8" behind="-2722" id="0ce4113d-34c8-4272-b658-3b929238dbd3" first_name="Brad" last_name="Keselowski" full_name="Brad Keselowski" status="ACT" points="2318" starts="36" wins="3" poles="3" stage_wins="4" chase_bonus="24" chase_wins="0" chase_stage_wins="0" top_5="13" top_10="19" top_15="23" top_20="31" dnf="4" laps_led="1085" laps_completed="9749" money="0.0" avg_start_position="10.0" avg_finish_position="12.8611" avg_laps_completed="270.8056" laps_led_pct="11.13" in_chase="false"/>
    <driver rank="9" behind="-2750" id="bcf5b54b-bbbe-4653-aade-a7364e946056" first_name="Clint" last_name="Bowyer" full_name="Clint Bowyer" status="ACT" points="2290" starts="36" wins="0" poles="1" stage_wins="1" chase_bonus="1" chase_wins="0" chase_stage_wins="1" top_5="7" top_10="18" top_15="23" top_20="26" dnf="7" laps_led="138" laps_completed="9874" money="0.0" avg_start_position="10.7222" avg_finish_position="15.1667" avg_laps_completed="274.2778" laps_led_pct="1.4" in_chase="false"/>
    <driver rank="10" behind="-2765" id="5fd3e3fb-322f-4157-ae41-9317fba1997d" first_name="Chase" last_name="Elliott" full_name="Chase Elliott" status="ACT" points="2275" starts="36" wins="3" poles="4" stage_wins="5" chase_bonus="24" chase_wins="1" chase_stage_wins="1" top_5="11" top_10="15" top_15="24" top_20="28" dnf="6" laps_led="600" laps_completed="9497" money="0.0" avg_start_position="10.8889" avg_finish_position="15.1389" avg_laps_completed="263.8056" laps_led_pct="6.32" in_chase="false"/>
    <driver rank="11" behind="-2766" id="c9bf58a8-66b6-4d75-a441-c13130ded990" first_name="William" last_name="Byron" full_name="William Byron" status="ACT" points="2274" starts="36" wins="0" poles="5" stage_wins="2" chase_bonus="2" chase_wins="0" chase_stage_wins="1" top_5="5" top_10="13" top_15="17" top_20="26" dnf="3" laps_led="233" laps_completed="10149" money="0.0" avg_start_position="12.4167" avg_finish_position="14.8889" avg_laps_completed="281.9167" laps_led_pct="2.3" in_chase="false"/>
    <driver rank="12" behind="-2783" id="3ebef96f-43b4-422a-9d0c-db0127b25384" first_name="Alex" last_name="Bowman" full_name="Alex Bowman" status="ACT" points="2257" starts="36" wins="1" poles="0" stage_wins="0" chase_bonus="5" chase_wins="0" chase_stage_wins="0" top_5="7" top_10="12" top_15="22" top_20="27" dnf="2" laps_led="200" laps_completed="10028" money="0.0" avg_start_position="13.1111" avg_finish_position="14.3611" avg_laps_completed="278.5556" laps_led_pct="1.99" in_chase="false"/>
    <driver rank="13" behind="-2803" id="8e76a45f-596e-4b56-9eb6-0623e45bf89c" first_name="Kurt" last_name="Busch" full_name="Kurt Busch" status="ACT" points="2237" starts="36" wins="1" poles="0" stage_wins="3" chase_bonus="11" chase_wins="0" chase_stage_wins="0" top_5="6" top_10="18" top_15="25" top_20="28" dnf="2" laps_led="212" laps_completed="10140" money="0.0" avg_start_position="12.6944" avg_finish_position="13.1111" avg_laps_completed="281.6667" laps_led_pct="2.09" in_chase="false"/>
    <driver rank="14" behind="-2806" id="e128a081-a2e8-4809-8038-8c936049bf7c" first_name="Aric" last_name="Almirola" full_name="Aric Almirola" status="ACT" points="2234" starts="36" wins="0" poles="1" stage_wins="2" chase_bonus="2" chase_wins="0" chase_stage_wins="1" top_5="3" top_10="12" top_15="21" top_20="27" dnf="3" laps_led="180" laps_completed="9564" money="0.0" avg_start_position="10.5" avg_finish_position="15.4167" avg_laps_completed="265.6667" laps_led_pct="1.88" in_chase="false"/>
    <driver rank="15" behind="-2821" id="2e6f5ea3-ea6e-48d2-85ec-2e89c2fa02b4" first_name="Ryan" last_name="Newman" full_name="Ryan Newman" status="ACT" points="2219" starts="36" wins="0" poles="0" stage_wins="0" chase_bonus="0" chase_wins="0" chase_stage_wins="0" top_5="3" top_10="14" top_15="22" top_20="27" dnf="1" laps_led="19" laps_completed="10030" money="0.0" avg_start_position="19.9167" avg_finish_position="14.5556" avg_laps_completed="278.6111" laps_led_pct="0.19" in_chase="false"/>
    <driver rank="16" behind="-2846" id="e595780e-baa7-4988-9a19-311fef7414d5" first_name="Erik" last_name="Jones" full_name="Erik Jones" status="ACT" points="2194" starts="36" wins="1" poles="0" stage_wins="0" chase_bonus="5" chase_wins="0" chase_stage_wins="0" top_5="10" top_10="17" top_15="20" top_20="24" dnf="4" laps_led="172" laps_completed="9606" money="0.0" avg_start_position="14.9167" avg_finish_position="16.25" avg_laps_completed="266.8333" laps_led_pct="1.79" in_chase="false"/>
    <driver rank="17" behind="-4194" id="ebd0a08d-5308-442e-a2ae-2e40aafb3100" first_name="Daniel" last_name="Suarez" full_name="Daniel Suarez" status="ACT" points="846" starts="36" wins="0" poles="1" stage_wins="0" chase_bonus="0" chase_wins="0" chase_stage_wins="0" top_5="4" top_10="11" top_15="20" top_20="27" dnf="4" laps_led="166" laps_completed="10143" money="0.0" avg_start_position="14.2222" avg_finish_position="16.3889" avg_laps_completed="281.75" laps_led_pct="1.64" in_chase="false"/>
    <driver rank="18" behind="-4205" id="057da6c6-ad81-4c65-b6b1-64b6da9e2ee7" first_name="Jimmie" last_name="Johnson" full_name="Jimmie Johnson" status="ACT" points="835" starts="36" wins="0" poles="1" stage_wins="1" chase_bonus="1" chase_wins="0" chase_stage_wins="0" top_5="3" top_10="12" top_15="20" top_20="26" dnf="4" laps_led="131" laps_completed="9798" money="0.0" avg_start_position="13.5" avg_finish_position="17.3611" avg_laps_completed="272.1667" laps_led_pct="1.34" in_chase="false"/>
    <driver rank="19" behind="-4263" id="cb239c48-8ccb-4043-a221-531b0da78765" first_name="Paul" last_name="Menard" full_name="Paul Menard" status="ACT" points="777" starts="36" wins="0" poles="0" stage_wins="0" chase_bonus="0" chase_wins="0" chase_stage_wins="0" top_5="0" top_10="4" top_15="15" top_20="29" dnf="1" laps_led="11" laps_completed="10217" money="0.0" avg_start_position="16.5833" avg_finish_position="16.5556" avg_laps_completed="283.8056" laps_led_pct="0.11" in_chase="false"/>
    <driver rank="20" behind="-4311" id="25cfebb6-24e5-429c-a9db-c276bab0e228" first_name="Chris" last_name="Buescher" full_name="Chris Buescher" status="ACT" points="729" starts="36" wins="0" poles="0" stage_wins="0" chase_bonus="0" chase_wins="0" chase_stage_wins="0" top_5="0" top_10="4" top_15="12" top_20="28" dnf="4" laps_led="13" laps_completed="10038" money="0.0" avg_start_position="21.6111" avg_finish_position="17.8333" avg_laps_completed="278.8333" laps_led_pct="0.13" in_chase="false"/>
    <driver rank="21" behind="-4340" id="8853e676-384e-4d08-8808-970fd111f36a" first_name="Austin" last_name="Dillon" full_name="Austin Dillon" status="ACT" points="700" starts="36" wins="0" poles="3" stage_wins="2" chase_bonus="2" chase_wins="0" chase_stage_wins="0" top_5="0" top_10="6" top_15="14" top_20="21" dnf="3" laps_led="70" laps_completed="9832" money="0.0" avg_start_position="16.4722" avg_finish_position="19.4722" avg_laps_completed="273.1111" laps_led_pct="0.71" in_chase="false"/>
    <driver rank="22" behind="-4341" id="06c9c0f9-392a-4f0e-aae7-39bb417af02f" first_name="Matt" last_name="DiBenedetto" full_name="Matt DiBenedetto" status="ACT" points="699" starts="36" wins="0" poles="0" stage_wins="0" chase_bonus="0" chase_wins="0" chase_stage_wins="0" top_5="3" top_10="7" top_15="13" top_20="23" dnf="5" laps_led="152" laps_completed="9839" money="0.0" avg_start_position="20.4722" avg_finish_position="18.3056" avg_laps_completed="273.3056" laps_led_pct="1.54" in_chase="false"/>
    <driver rank="23" behind="-4361" id="0cdae85e-0b1d-44d7-9614-a49aff66aeb5" first_name="Ricky" last_name="Stenhouse" full_name="Ricky Stenhouse Jr" status="ACT" points="679" starts="36" wins="0" poles="0" stage_wins="0" chase_bonus="0" chase_wins="0" chase_stage_wins="0" top_5="1" top_10="3" top_15="12" top_20="21" dnf="5" laps_led="109" laps_completed="9526" money="0.0" avg_start_position="15.0556" avg_finish_position="20.4722" avg_laps_completed="264.6111" laps_led_pct="1.14" in_chase="false"/>
    <driver rank="24" behind="-4427" id="bfcb8d32-fab0-4bfa-be14-cf9466e1d886" first_name="Ty" last_name="Dillon" full_name="Ty Dillon" status="ACT" points="613" starts="36" wins="0" poles="0" stage_wins="2" chase_bonus="2" chase_wins="0" chase_stage_wins="0" top_5="1" top_10="3" top_15="9" top_20="16" dnf="0" laps_led="14" laps_completed="10171" money="0.0" avg_start_position="23.5278" avg_finish_position="20.5556" avg_laps_completed="282.5278" laps_led_pct="0.14" in_chase="false"/>
    <driver rank="25" behind="-4510" id="460d88fe-cf23-495e-8f04-98729874023c" first_name="Daniel" last_name="Hemric" full_name="Daniel Hemric" status="ACT" points="530" starts="36" wins="0" poles="1" stage_wins="0" chase_bonus="0" chase_wins="0" chase_stage_wins="0" top_5="1" top_10="2" top_15="7" top_20="16" dnf="5" laps_led="22" laps_completed="9825" money="0.0" avg_start_position="18.1389" avg_finish_position="22.4722" avg_laps_completed="272.9167" laps_led_pct="0.22" in_chase="false"/>
    <driver rank="26" behind="-4533" id="e28a64ca-c622-4b28-b0d9-28bc9390f9e4" first_name="Ryan" last_name="Preece" full_name="Ryan Preece" status="ACT" points="507" starts="36" wins="0" poles="0" stage_wins="0" chase_bonus="0" chase_wins="0" chase_stage_wins="0" top_5="1" top_10="3" top_15="4" top_20="11" dnf="6" laps_led="1" laps_completed="9930" money="0.0" avg_start_position="24.3611" avg_finish_position="23.0556" avg_laps_completed="275.8333" laps_led_pct="0.01" in_chase="false"/>
    <driver rank="27" behind="-4555" id="96fdd8d7-3776-42b8-baf2-6b4e2cf2d83d" first_name="Michael" last_name="McDowell" full_name="Michael McDowell" status="ACT" points="485" starts="36" wins="0" poles="0" stage_wins="0" chase_bonus="0" chase_wins="0" chase_stage_wins="0" top_5="2" top_10="2" top_15="5" top_20="10" dnf="5" laps_led="18" laps_completed="9366" money="0.0" avg_start_position="20.8611" avg_finish_position="24.1667" avg_laps_completed="260.1667" laps_led_pct="0.19" in_chase="false"/>
    <driver rank="28" behind="-4603" id="939e647d-756f-41d7-ad65-609344f64bd5" first_name="Bubba" last_name="Wallace" full_name="Bubba Wallace" status="ACT" points="437" starts="36" wins="0" poles="0" stage_wins="0" chase_bonus="0" chase_wins="0" chase_stage_wins="0" top_5="1" top_10="1" top_15="5" top_20="8" dnf="3" laps_led="1" laps_completed="9939" money="0.0" avg_start_position="24.3333" avg_finish_position="23.9444" avg_laps_completed="276.0833" laps_led_pct="0.01" in_chase="false"/>
    <driver rank="29" behind="-4639" id="68b9a7ed-c810-4c0d-a330-7a99b90c2587" first_name="Corey" last_name="Lajoie" full_name="Corey Lajoie" status="ACT" points="401" starts="36" wins="0" poles="0" stage_wins="0" chase_bonus="0" chase_wins="0" chase_stage_wins="0" top_5="0" top_10="2" top_15="4" top_20="7" dnf="4" laps_led="0" laps_completed="9541" money="0.0" avg_start_position="29.6667" avg_finish_position="25.9167" avg_laps_completed="265.0278" laps_led_pct="0.0" in_chase="false"/>
    <driver rank="30" behind="-4652" id="25884070-3ded-4fdc-9370-d09428ac95e4" first_name="David" last_name="Ragan" full_name="David Ragan" status="ACT" points="388" starts="36" wins="0" poles="0" stage_wins="0" chase_bonus="0" chase_wins="0" chase_stage_wins="0" top_5="0" top_10="0" top_15="2" top_20="7" dnf="8" laps_led="3" laps_completed="9710" money="0.0" avg_start_position="21.8333" avg_finish_position="26.2778" avg_laps_completed="269.7222" laps_led_pct="0.03" in_chase="false"/>
    <driver rank="31" behind="-4688" id="3560705d-b150-4bd3-8275-6093f01524bc" first_name="Matt" last_name="Tifft" full_name="Matt Tifft" status="ACT" points="352" starts="32" wins="0" poles="0" stage_wins="0" chase_bonus="0" chase_wins="0" chase_stage_wins="0" top_5="0" top_10="1" top_15="2" top_20="5" dnf="4" laps_led="1" laps_completed="8502" money="0.0" avg_start_position="28.1875" avg_finish_position="26.0313" avg_laps_completed="265.6875" laps_led_pct="0.01" in_chase="false"/>
    <driver rank="32" behind="-4922" id="1a618e86-838d-4983-9b52-011a67cccf7a" first_name="Reed" last_name="Sorenson" full_name="Reed Sorenson" status="ACT" points="118" starts="25" wins="0" poles="0" stage_wins="0" chase_bonus="0" chase_wins="0" chase_stage_wins="0" top_5="0" top_10="0" top_15="0" top_20="1" dnf="9" laps_led="0" laps_completed="5854" money="0.0" avg_start_position="35.84" avg_finish_position="32.72" avg_laps_completed="234.16" laps_led_pct="0.0" in_chase="false"/>
    <driver rank="33" behind="-4963" id="41358418-6638-433d-a26d-0e12f546d1e6" first_name="Quin" last_name="Houff" full_name="Quin Houff" status="ACT" points="77" starts="17" wins="0" poles="0" stage_wins="0" chase_bonus="0" chase_wins="0" chase_stage_wins="0" top_5="0" top_10="0" top_15="0" top_20="0" dnf="3" laps_led="0" laps_completed="4519" money="0.0" avg_start_position="33.7059" avg_finish_position="32.6471" avg_laps_completed="265.8235" laps_led_pct="0.0" in_chase="false"/>
    <driver rank="34" behind="-5021" id="f8d8ff36-bfcf-4d98-8eb2-353f1e8d3c34" first_name="Jamie" last_name="McMurray" full_name="Jamie McMurray" status="ACT" points="19" starts="1" wins="0" poles="0" stage_wins="0" chase_bonus="0" chase_wins="0" chase_stage_wins="0" top_5="0" top_10="0" top_15="0" top_20="0" dnf="1" laps_led="6" laps_completed="198" money="0.0" avg_start_position="16.0" avg_finish_position="22.0" avg_laps_completed="198.0" laps_led_pct="3.03" in_chase="false"/>
    <driver rank="35" behind="-5023" id="4f63e2cc-e20e-43a4-ad00-1f54b6f7461d" first_name="Austin" last_name="Theriault" full_name="Austin Theriault" status="ACT" points="17" starts="5" wins="0" poles="0" stage_wins="0" chase_bonus="0" chase_wins="0" chase_stage_wins="0" top_5="0" top_10="0" top_15="0" top_20="0" dnf="2" laps_led="1" laps_completed="1090" money="0.0" avg_start_position="33.4" avg_finish_position="33.6" avg_laps_completed="218.0" laps_led_pct="0.09" in_chase="false"/>
    <driver rank="36" behind="-5031" id="50d079fb-f661-40d4-812e-207beef1a7e3" first_name="Andy" last_name="Seuss" full_name="Andy Seuss" status="ACT" points="9" starts="1" wins="0" poles="0" stage_wins="0" chase_bonus="0" chase_wins="0" chase_stage_wins="0" top_5="0" top_10="0" top_15="0" top_20="0" dnf="0" laps_led="0" laps_completed="291" money="0.0" avg_start_position="35.0" avg_finish_position="28.0" avg_laps_completed="291.0" laps_led_pct="0.0" in_chase="false"/>
    <driver rank="37" behind="-5032" id="be1588ce-83ab-4aef-8016-9d3a5f2d10d0" first_name="Drew" last_name="Herring" full_name="Drew Herring" status="ACT" points="8" starts="1" wins="0" poles="0" stage_wins="0" chase_bonus="0" chase_wins="0" chase_stage_wins="0" top_5="0" top_10="0" top_15="0" top_20="0" dnf="0" laps_led="0" laps_completed="262" money="0.0" avg_start_position="37.0" avg_finish_position="29.0" avg_laps_completed="262.0" laps_led_pct="0.0" in_chase="false"/>
    <driver rank="38" behind="-5034" id="986c20d7-178a-4d77-bb46-dde8d453dda5" first_name="Blake" last_name="Jones" full_name="Blake Jones" status="ACT" points="6" starts="1" wins="0" poles="0" stage_wins="0" chase_bonus="0" chase_wins="0" chase_stage_wins="0" top_5="0" top_10="0" top_15="0" top_20="0" dnf="0" laps_led="0" laps_completed="179" money="0.0" avg_start_position="35.0" avg_finish_position="31.0" avg_laps_completed="179.0" laps_led_pct="0.0" in_chase="false"/>
    <driver rank="39" behind="-5038" id="147b907c-98c4-4890-9bb7-0db3b210b785" first_name="Stanton" last_name="Barrett" full_name="Stanton Barrett" status="ACT" points="2" starts="1" wins="0" poles="0" stage_wins="0" chase_bonus="0" chase_wins="0" chase_stage_wins="0" top_5="0" top_10="0" top_15="0" top_20="0" dnf="1" laps_led="0" laps_completed="132" money="0.0" avg_start_position="39.0" avg_finish_position="35.0" avg_laps_completed="132.0" laps_led_pct="0.0" in_chase="false"/>
    <driver rank="40" behind="-5039" id="0b2a3633-d6cc-4217-bbd6-44f6ec160ed9" first_name="Casey" last_name="Mears" full_name="Casey Mears" status="ACT" points="1" starts="1" wins="0" poles="0" stage_wins="0" chase_bonus="0" chase_wins="0" chase_stage_wins="0" top_5="0" top_10="0" top_15="0" top_20="0" dnf="1" laps_led="0" laps_completed="104" money="0.0" avg_start_position="40.0" avg_finish_position="40.0" avg_laps_completed="104.0" laps_led_pct="0.0" in_chase="false"/>
    <driver rank="41" behind="-5040" id="6e3ed92a-ee25-4dea-b116-d493ebccba07" first_name="Justin" last_name="Haley" full_name="Justin Haley" status="ACT" points="0" starts="3" wins="1" poles="0" stage_wins="0" chase_bonus="5" chase_wins="0" chase_stage_wins="0" top_5="1" top_10="1" top_15="1" top_20="1" dnf="1" laps_led="1" laps_completed="395" money="0.0" avg_start_position="35.0" avg_finish_position="22.3333" avg_laps_completed="131.6667" laps_led_pct="0.25" in_chase="false"/>
    <driver rank="42" behind="-5040" id="66d6cb11-de3a-4816-9c58-003a76634560" first_name="Brendan" last_name="Gaughan" full_name="Brendan Gaughan" status="ACT" points="0" starts="4" wins="0" poles="0" stage_wins="0" chase_bonus="0" chase_wins="0" chase_stage_wins="0" top_5="0" top_10="1" top_15="1" top_20="2" dnf="2" laps_led="5" laps_completed="692" money="0.0" avg_start_position="31.5" avg_finish_position="19.25" avg_laps_completed="173.0" laps_led_pct="0.72" in_chase="false"/>
    <driver rank="43" behind="-5040" id="b030a8df-e7de-44a4-9f59-34bb9fd227d0" first_name="Tyler" last_name="Reddick" full_name="Tyler Reddick" status="ACT" points="0" starts="2" wins="0" poles="0" stage_wins="0" chase_bonus="0" chase_wins="0" chase_stage_wins="0" top_5="0" top_10="1" top_15="1" top_20="1" dnf="1" laps_led="0" laps_completed="462" money="0.0" avg_start_position="30.0" avg_finish_position="18.0" avg_laps_completed="231.0" laps_led_pct="0.0" in_chase="false"/>
    <driver rank="44" behind="-5040" id="fb6c45e9-990e-46e3-88df-174449c13334" first_name="Ross" last_name="Chastain" full_name="Ross Chastain" status="ACT" points="0" starts="35" wins="0" poles="0" stage_wins="0" chase_bonus="0" chase_wins="0" chase_stage_wins="0" top_5="0" top_10="1" top_15="2" top_20="2" dnf="3" laps_led="11" laps_completed="9332" money="0.0" avg_start_position="33.5714" avg_finish_position="28.2" avg_laps_completed="266.6286" laps_led_pct="0.12" in_chase="false"/>
    <driver rank="45" behind="-5040" id="f07507f1-0a84-4b90-929d-7389dc5baab4" first_name="Landon" last_name="Cassill" full_name="Landon Cassill" status="ACT" points="0" starts="36" wins="0" poles="0" stage_wins="0" chase_bonus="0" chase_wins="0" chase_stage_wins="0" top_5="0" top_10="0" top_15="2" top_20="2" dnf="4" laps_led="1" laps_completed="9419" money="0.0" avg_start_position="30.9167" avg_finish_position="29.2778" avg_laps_completed="261.6389" laps_led_pct="0.01" in_chase="false"/>
    <driver rank="46" behind="-5040" id="a602316b-3712-4de2-9098-7fcd887e7bd2" first_name="Parker" last_name="Kligerman" full_name="Parker Kligerman" status="ACT" points="0" starts="14" wins="0" poles="0" stage_wins="0" chase_bonus="0" chase_wins="0" chase_stage_wins="0" top_5="0" top_10="0" top_15="2" top_20="2" dnf="2" laps_led="0" laps_completed="3002" money="0.0" avg_start_position="32.0" avg_finish_position="26.5" avg_laps_completed="214.4286" laps_led_pct="0.0" in_chase="false"/>
    <driver rank="47" behind="-5040" id="32251b56-7387-4ade-8482-0917553218f4" first_name="JJ" last_name="Yeley" full_name="JJ Yeley" status="ACT" points="0" starts="15" wins="0" poles="0" stage_wins="0" chase_bonus="0" chase_wins="0" chase_stage_wins="0" top_5="0" top_10="0" top_15="1" top_20="1" dnf="1" laps_led="0" laps_completed="4086" money="0.0" avg_start_position="35.7333" avg_finish_position="29.2667" avg_laps_completed="272.4" laps_led_pct="0.0" in_chase="false"/>
    <driver rank="48" behind="-5040" id="e4b9e60e-d4c2-4b42-93c3-0fa1f2695160" first_name="Bayley" last_name="Currey" full_name="Bayley Currey" status="ACT" points="0" starts="10" wins="0" poles="0" stage_wins="0" chase_bonus="0" chase_wins="0" chase_stage_wins="0" top_5="0" top_10="0" top_15="0" top_20="0" dnf="1" laps_led="0" laps_completed="2992" money="0.0" avg_start_position="31.9" avg_finish_position="31.9" avg_laps_completed="299.2" laps_led_pct="0.0" in_chase="false"/>
    <driver rank="49" behind="-5040" id="a9988edd-7707-4a75-9ee5-d3a8cae0c8aa" first_name="Timmy" last_name="Hill" full_name="Timmy Hill" status="ACT" points="0" starts="8" wins="0" poles="0" stage_wins="0" chase_bonus="0" chase_wins="0" chase_stage_wins="0" top_5="0" top_10="0" top_15="0" top_20="0" dnf="5" laps_led="0" laps_completed="1722" money="0.0" avg_start_position="37.625" avg_finish_position="35.625" avg_laps_completed="215.25" laps_led_pct="0.0" in_chase="false"/>
    <driver rank="50" behind="-5040" id="5ae1a122-28a3-461b-82e0-955c0d1132fa" first_name="BJ" last_name="McLeod" full_name="BJ McLeod" status="ACT" points="0" starts="18" wins="0" poles="0" stage_wins="0" chase_bonus="0" chase_wins="0" chase_stage_wins="0" top_5="0" top_10="0" top_15="0" top_20="1" dnf="4" laps_led="0" laps_completed="4503" money="0.0" avg_start_position="34.8889" avg_finish_position="31.7778" avg_laps_completed="250.1667" laps_led_pct="0.0" in_chase="false"/>
    <driver rank="51" behind="-5040" id="fa1dba10-512b-4cfd-bcb7-c8e4963a209d" first_name="Cody" last_name="Ware" full_name="Cody Ware" status="ACT" points="0" starts="13" wins="0" poles="0" stage_wins="0" chase_bonus="0" chase_wins="0" chase_stage_wins="0" top_5="0" top_10="0" top_15="0" top_20="0" dnf="4" laps_led="0" laps_completed="2465" money="0.0" avg_start_position="34.5385" avg_finish_position="34.7692" avg_laps_completed="189.6154" laps_led_pct="0.0" in_chase="false"/>
    <driver rank="52" behind="-5040" id="788d2f69-6260-40c0-ad66-631a9cc0c24d" first_name="Joey" last_name="Gase" full_name="Joey Gase" status="ACT" points="0" starts="11" wins="0" poles="0" stage_wins="0" chase_bonus="0" chase_wins="0" chase_stage_wins="0" top_5="0" top_10="0" top_15="0" top_20="0" dnf="4" laps_led="0" laps_completed="2338" money="0.0" avg_start_position="38.3636" avg_finish_position="35.1818" avg_laps_completed="212.5455" laps_led_pct="0.0" in_chase="false"/>
    <driver rank="53" behind="-5040" id="6334f9f0-8b97-4020-8204-2ba30e7dd4ba" first_name="John H." last_name="Nemechek" full_name="John H. Nemechek" status="ACT" points="0" starts="3" wins="0" poles="0" stage_wins="0" chase_bonus="0" chase_wins="0" chase_stage_wins="0" top_5="0" top_10="0" top_15="0" top_20="0" dnf="0" laps_led="0" laps_completed="904" money="0.0" avg_start_position="28.3333" avg_finish_position="23.6667" avg_laps_completed="301.3333" laps_led_pct="0.0" in_chase="false"/>
    <driver rank="54" behind="-5040" id="2e33a0c7-05f0-4887-bcbd-b64606114676" first_name="Jeffrey" last_name="Earnhardt" full_name="Jeffrey Earnhardt" status="ACT" points="0" starts="1" wins="0" poles="0" stage_wins="0" chase_bonus="0" chase_wins="0" chase_stage_wins="0" top_5="0" top_10="0" top_15="0" top_20="0" dnf="1" laps_led="0" laps_completed="187" money="0.0" avg_start_position="33.0" avg_finish_position="22.0" avg_laps_completed="187.0" laps_led_pct="0.0" in_chase="false"/>
    <driver rank="55" behind="-5040" id="81228be2-3223-4e34-80d3-e68f616e8fc6" first_name="Ryan" last_name="Sieg" full_name="Ryan Sieg" status="ACT" points="0" starts="1" wins="0" poles="0" stage_wins="0" chase_bonus="0" chase_wins="0" chase_stage_wins="0" top_5="0" top_10="0" top_15="0" top_20="0" dnf="0" laps_led="0" laps_completed="157" money="0.0" avg_start_position="36.0" avg_finish_position="24.0" avg_laps_completed="157.0" laps_led_pct="0.0" in_chase="false"/>
    <driver rank="56" behind="-5040" id="b5610b89-dded-41b1-bb85-bac0ccf63015" first_name="Matt" last_name="Crafton" full_name="Matt Crafton" status="ACT" points="0" starts="1" wins="0" poles="0" stage_wins="0" chase_bonus="0" chase_wins="0" chase_stage_wins="0" top_5="0" top_10="0" top_15="0" top_20="0" dnf="0" laps_led="0" laps_completed="495" money="0.0" avg_start_position="29.0" avg_finish_position="25.0" avg_laps_completed="495.0" laps_led_pct="0.0" in_chase="false"/>
    <driver rank="57" behind="-5040" id="35a6fe75-7b32-4b7b-af0c-e68cb0891f7a" first_name="Garrett" last_name="Smithley" full_name="Garrett Smithley" status="ACT" points="0" starts="14" wins="0" poles="0" stage_wins="0" chase_bonus="0" chase_wins="0" chase_stage_wins="0" top_5="0" top_10="0" top_15="0" top_20="0" dnf="2" laps_led="0" laps_completed="3637" money="0.0" avg_start_position="35.9286" avg_finish_position="33.5" avg_laps_completed="259.7857" laps_led_pct="0.0" in_chase="false"/>
    <driver rank="58" behind="-5040" id="1fb0e2af-80f6-4c6b-bf02-c2c96a53c1ff" first_name="Joe" last_name="Nemechek" full_name="Joe Nemechek" status="ACT" points="0" starts="7" wins="0" poles="0" stage_wins="0" chase_bonus="0" chase_wins="0" chase_stage_wins="0" top_5="0" top_10="0" top_15="0" top_20="0" dnf="1" laps_led="0" laps_completed="1951" money="0.0" avg_start_position="36.5714" avg_finish_position="32.4286" avg_laps_completed="278.7143" laps_led_pct="0.0" in_chase="false"/>
    <driver rank="59" behind="-5040" id="d259900a-e2e7-4612-b201-178bb80a862c" first_name="Josh" last_name="Bilicki" full_name="Josh Bilicki" status="ACT" points="0" starts="10" wins="0" poles="0" stage_wins="0" chase_bonus="0" chase_wins="0" chase_stage_wins="0" top_5="0" top_10="0" top_15="0" top_20="0" dnf="4" laps_led="0" laps_completed="2125" money="0.0" avg_start_position="35.4" avg_finish_position="33.7" avg_laps_completed="212.5" laps_led_pct="0.0" in_chase="false"/>
    <driver rank="60" behind="-5040" id="c7beb5c5-3d88-4dec-881f-793e68ee2d19" first_name="Jeb" last_name="Burton" full_name="Jeb Burton" status="ACT" points="0" starts="2" wins="0" poles="0" stage_wins="0" chase_bonus="0" chase_wins="0" chase_stage_wins="0" top_5="0" top_10="0" top_15="0" top_20="0" dnf="1" laps_led="0" laps_completed="555" money="0.0" avg_start_position="31.5" avg_finish_position="33.0" avg_laps_completed="277.5" laps_led_pct="0.0" in_chase="false"/>
    <driver rank="61" behind="-5040" id="614d3671-2b12-42d6-915e-2521b859e370" first_name="Kyle" last_name="Weatherman" full_name="Kyle Weatherman" status="ACT" points="0" starts="2" wins="0" poles="0" stage_wins="0" chase_bonus="0" chase_wins="0" chase_stage_wins="0" top_5="0" top_10="0" top_15="0" top_20="0" dnf="1" laps_led="0" laps_completed="543" money="0.0" avg_start_position="35.5" avg_finish_position="33.5" avg_laps_completed="271.5" laps_led_pct="0.0" in_chase="false"/>
    <driver rank="62" behind="-5040" id="46f77b78-961b-48cc-8681-b971511d2d5e" first_name="D.J." last_name="Kennington" full_name="D.J. Kennington" status="ACT" points="0" starts="1" wins="0" poles="0" stage_wins="0" chase_bonus="0" chase_wins="0" chase_stage_wins="0" top_5="0" top_10="0" top_15="0" top_20="0" dnf="0" laps_led="0" laps_completed="489" money="0.0" avg_start_position="35.0" avg_finish_position="32.0" avg_laps_completed="489.0" laps_led_pct="0.0" in_chase="false"/>
    <driver rank="63" behind="-5040" id="ce805205-7fa6-46b7-980a-d3017d870be7" first_name="Spencer" last_name="Boyd" full_name="Spencer Boyd" status="ACT" points="0" starts="3" wins="0" poles="0" stage_wins="0" chase_bonus="0" chase_wins="0" chase_stage_wins="0" top_5="0" top_10="0" top_15="0" top_20="0" dnf="2" laps_led="0" laps_completed="564" money="0.0" avg_start_position="36.6667" avg_finish_position="37.3333" avg_laps_completed="188.0" laps_led_pct="0.0" in_chase="false"/>
    <driver rank="64" behind="-5040" id="6e5a779b-11fa-46bf-bfc9-51efedfe66c4" first_name="Gray" last_name="Gaulding" full_name="Gray Gaulding" status="ACT" points="0" starts="1" wins="0" poles="0" stage_wins="0" chase_bonus="0" chase_wins="0" chase_stage_wins="0" top_5="0" top_10="0" top_15="0" top_20="0" dnf="1" laps_led="0" laps_completed="142" money="0.0" avg_start_position="33.0" avg_finish_position="36.0" avg_laps_completed="142.0" laps_led_pct="0.0" in_chase="false"/>
  </season>
</series>
<!-- Generation ended @ 2021-06-20 02:13:34 UTC -->
